MANIFEST.in
README.md
setup.py
djangocms_simple_gallery/__init__.py
djangocms_simple_gallery/admin.py
djangocms_simple_gallery/cms_plugins.py
djangocms_simple_gallery/models.py
djangocms_simple_gallery/settings.py
djangocms_simple_gallery/south_introspections.py
djangocms_simple_gallery/validators.py
djangocms_simple_gallery.egg-info/PKG-INFO
djangocms_simple_gallery.egg-info/SOURCES.txt
djangocms_simple_gallery.egg-info/dependency_links.txt
djangocms_simple_gallery.egg-info/requires.txt
djangocms_simple_gallery.egg-info/top_level.txt
djangocms_simple_gallery/migrations/0001_initial.py
djangocms_simple_gallery/migrations/0002_auto__add_field_slide_description.py
djangocms_simple_gallery/migrations/0003_auto__chg_field_slide_url.py
djangocms_simple_gallery/migrations/__init__.py
djangocms_simple_gallery/static/css/djangocms_gallery/simple.css
djangocms_simple_gallery/static/js/cl.gallery.js
djangocms_simple_gallery/static/js/libs/class.min.js
djangocms_simple_gallery/static/js/libs/jquery.min.js
djangocms_simple_gallery/templates/djangocms_simple_gallery/default.html
djangocms_simple_gallery/templates/djangocms_simple_gallery/gallery_base.html