Metadata-Version: 1.0
Name: djangocms-simple-gallery
Version: 1.1.1
Summary: Simple gallery plugin for the django-cms.
Home-page: https://github.com/divio/djangocms-simple-gallery
Author: Pascal Mouret
Author-email: pascal.mouret@divio.ch
License: UNKNOWN
Platform: OS Independent
Classifier: Environment :: Web Environment
Classifier: Framework :: Django
Classifier: Intended Audience :: Developers
Classifier: License :: OSI Approved :: BSD License
Classifier: Operating System :: OS Independent
Classifier: Programming Language :: Python
Classifier: Topic :: Internet :: WWW/HTTP :: Dynamic Content
Classifier: Topic :: Software Development
Classifier: Topic :: Software Development :: Libraries :: Application Frameworks
Classifier: Development Status :: 5 - Production/Stable
